datadings/__init__.py
datadings/commands/__init__.py
datadings/commands/bench.py
datadings/commands/cat.py
datadings/commands/convert_index.py
datadings/commands/merge.py
datadings/commands/sample.py
datadings/commands/shuffle.py
datadings/commands/split.py
datadings/commands/write.py
datadings/index/__init__.py
datadings/reader/__init__.py
datadings/reader/augment.py
datadings/reader/directory.py
datadings/reader/list.py
datadings/reader/msgpack.py
datadings/reader/reader.py
datadings/reader/sharded.py
datadings/reader/zipfile.py
datadings/sets/ADE20k.py
datadings/sets/ADE20k_counts.json.xz
datadings/sets/ADE20k_scenelabels.json.gz
datadings/sets/ADE20k_write.py
datadings/sets/ANP460.py
datadings/sets/ANP460_write.py
datadings/sets/CAMVID.py
datadings/sets/CAMVID_write.py
datadings/sets/CAT2000.py
datadings/sets/CAT2000_write.py
datadings/sets/CIFAR10.py
datadings/sets/CIFAR100.py
datadings/sets/CIFAR100_write.py
datadings/sets/CIFAR10_write.py
datadings/sets/Cityscapes.py
datadings/sets/Cityscapes_write.py
datadings/sets/Coutrot1.py
datadings/sets/Coutrot1_write.py
datadings/sets/FIGRIMFixation.py
datadings/sets/FIGRIMFixation_write.py
datadings/sets/ILSVRC2012.py
datadings/sets/ILSVRC2012_synsets.py
datadings/sets/ILSVRC2012_synsets.txt.xz
datadings/sets/ILSVRC2012_val.txt.xz
datadings/sets/ILSVRC2012_write.py
datadings/sets/ImageNet21k_create_meta.py
datadings/sets/ImageNet21k_synsets.json.xz
datadings/sets/ImageNet21k_synsets.py
datadings/sets/ImageNet21k_write.py
datadings/sets/InriaBuildings.py
datadings/sets/InriaBuildings_write.py
datadings/sets/MIT1003.py
datadings/sets/MIT1003_write.py
datadings/sets/MIT300.py
datadings/sets/MIT300_write.py
datadings/sets/Places2017.py
datadings/sets/Places2017_colors.json.gz
datadings/sets/Places2017_counts.json.gz
datadings/sets/Places2017_scenelabels.json.xz
datadings/sets/Places2017_write.py
datadings/sets/Places365.py
datadings/sets/Places365_classes.json.gz
datadings/sets/Places365_write.py
datadings/sets/RIT18.py
datadings-3.4.7.dist-info/licenses/LICENSE
datadings-3.4.7.dist-info/METADATA
datadings-3.4.7.dist-info/WHEEL
datadings-3.4.7.dist-info/entry_points.txt
datadings-3.4.7.dist-info/top_level.txt
datadings-3.4.7.dist-info/RECORD
