Metadata-Version: 2.4
Name: datadings
Version: 3.4.7
Summary:  datadings is a collection of tools to prepare datasets for machine learning. It's easy to use, space-efficient, and blazingly fast. 
Author: Joachim Folz
Author-email: joachim.folz@dfki.de
License: MIT
Project-URL: Documentation, https://datadings.readthedocs.io
Project-URL: Source, https://gitlab.com/jfolz/datadings
Project-URL: Tracker, https://gitlab.com/jfolz/datadings/issues
Keywords: datadings datasets data sets image classification semantic segmentation saliency
Classifier: Development Status :: 5 - Production/Stable
Classifier: Intended Audience :: Science/Research
Classifier: License :: OSI Approved :: MIT License
Classifier: Programming Language :: Python :: 3.6
Classifier: Programming Language :: Python :: 3.7
Classifier: Programming Language :: Python :: 3.8
Classifier: Programming Language :: Python :: 3.9
Classifier: Programming Language :: Python :: 3.10
License-File: LICENSE
Requires-Dist: gdown>=3.0.0
Requires-Dist: msgpack!=0.6.0,<2.0.0,>=0.5.0
Requires-Dist: msgpack_numpy<1.0.0,>=0.4.2
Requires-Dist: natsort>=4.0.4
Requires-Dist: numpy<3.0.0,>=1.17.0
Requires-Dist: Pillow>=7.0.0
Requires-Dist: requests<3.0.0,>=2.0.0
Requires-Dist: scipy<2.0.0,>=0.17.0
Requires-Dist: simplebloom<2.0.0,>=1.0.2
Requires-Dist: simplejpeg<2.0.0,>=1.2.5
Requires-Dist: tqdm<5.0.0,>=4.23.0
Requires-Dist: pyzmq>=18.1.1
Provides-Extra: geo
Requires-Dist: GDAL>=2.4.0; extra == "geo"
Dynamic: author
Dynamic: author-email
Dynamic: classifier
Dynamic: description
Dynamic: description-content-type
Dynamic: keywords
Dynamic: license
Dynamic: license-file
Dynamic: project-url
Dynamic: provides-extra
Dynamic: requires-dist
Dynamic: summary
